{
 "category": "Modules",
 "charts": [],
 "creation": "2022-09-12 17:46:52.659226",
 "developer_mode_only": 0,
 "disable_user_customization": 0,
 "docstatus": 0,
 "doctype": "Workspace",
 "extends_another_page": 0,
 "hide_custom": 0,
 "icon": "organization",
 "idx": 0,
 "is_default": 0,
 "is_standard": 1,
 "label": "Property Management",
 "links": [
  {
   "hidden": 0,
   "is_query_report": 0,
   "label": "Configuration",
   "link_type": "DocType",
   "onboard": 0,
   "type": "Card Break"
  },
  {
   "hidden": 0,
   "is_query_report": 0,
   "label": "Item",
   "link_to": "Item",
   "link_type": "DocType",
   "onboard": 1,
   "type": "Link"
  },
  {
   "hidden": 0,
   "is_query_report": 0,
   "label": "Item Group",
   "link_to": "Item Group",
   "link_type": "DocType",
   "onboard": 0,
   "type": "Link"
  },
  {
   "hidden": 0,
   "is_query_report": 0,
   "label": "Utility Type",
   "link_to": "Utility Type",
   "link_type": "DocType",
   "onboard": 0,
   "type": "Link"
  },
  {
   "hidden": 0,
   "is_query_report": 0,
   "label": "Place Type",
   "link_to": "Place Type",
   "link_type": "DocType",
   "onboard": 0,
   "type": "Link"
  },
  {
   "hidden": 0,
   "is_query_report": 0,
   "label": "Property Details",
   "link_type": "DocType",
   "onboard": 0,
   "type": "Card Break"
  },
  {
   "hidden": 0,
   "is_query_report": 0,
   "label": "Asset",
   "link_to": "Asset",
   "link_type": "DocType",
   "onboard": 1,
   "type": "Link"
  },
  {
   "hidden": 0,
   "is_query_report": 0,
   "label": "Asset Category",
   "link_to": "Asset Category",
   "link_type": "DocType",
   "onboard": 0,
   "type": "Link"
  },
  {
   "hidden": 0,
   "is_query_report": 0,
   "label": "Tenant Details",
   "link_type": "DocType",
   "onboard": 0,
   "type": "Card Break"
  },
  {
   "dependencies": "",
   "hidden": 0,
   "is_query_report": 0,
   "label": "Tenant",
   "link_to": "Customer",
   "link_type": "DocType",
   "onboard": 1,
   "type": "Link"
  },
  {
   "hidden": 0,
   "is_query_report": 0,
   "label": "Tenant Tenancy",
   "link_to": "Tenancy",
   "link_type": "DocType",
   "onboard": 1,
   "type": "Link"
  },
  {
   "hidden": 0,
   "is_query_report": 0,
   "label": "Landlord Details",
   "link_type": "DocType",
   "onboard": 0,
   "type": "Card Break"
  },
  {
   "hidden": 0,
   "is_query_report": 0,
   "label": "Landlord",
   "link_to": "Customer",
   "link_type": "DocType",
   "onboard": 1,
   "type": "Link"
  },
  {
   "dependencies": "",
   "hidden": 0,
   "is_query_report": 0,
   "label": "Landlord Tenancy",
   "link_to": "Tenancy",
   "link_type": "DocType",
   "onboard": 1,
   "type": "Link"
  },
  {
   "hidden": 0,
   "is_query_report": 0,
   "label": "Schedules",
   "link_to": "",
   "link_type": "DocType",
   "onboard": 0,
   "type": "Card Break"
  },
  {
   "hidden": 0,
   "is_query_report": 0,
   "label": "Tenancy Schedule",
   "link_to": "Event",
   "link_type": "DocType",
   "onboard": 0,
   "type": "Link"
  },
  {
   "hidden": 0,
   "is_query_report": 0,
   "label": "Reports",
   "link_type": "DocType",
   "onboard": 0,
   "type": "Card Break"
  },
  {
   "hidden": 0,
   "is_query_report": 1,
   "label": "Tenancy Details",
   "link_to": "Tenancy Details",
   "link_type": "Report",
   "onboard": 0,
   "type": "Link"
  },
  {
   "hidden": 0,
   "is_query_report": 1,
   "label": "Schedule-wise Tenancy Details",
   "link_to": "Schedule-wise Tenancy Details",
   "link_type": "Report",
   "onboard": 0,
   "type": "Link"
  },
  {
   "hidden": 0,
   "is_query_report": 1,
   "label": "Property Details",
   "link_to": "Property Details",
   "link_type": "Report",
   "onboard": 0,
   "type": "Link"
  },
  {
   "hidden": 0,
   "is_query_report": 1,
   "label": "Property Utility",
   "link_to": "Property Utility",
   "link_type": "Report",
   "onboard": 0,
   "type": "Link"
  },
  {
   "hidden": 0,
   "is_query_report": 1,
   "label": "Property Insurance",
   "link_to": "Property Insurance",
   "link_type": "Report",
   "onboard": 0,
   "type": "Link"
  },
  {
   "hidden": 0,
   "is_query_report": 1,
   "label": "Nearest Places of Property",
   "link_to": "Nearest Places of Property",
   "link_type": "Report",
   "onboard": 0,
   "type": "Link"
  },
  {
   "hidden": 0,
   "is_query_report": 0,
   "label": "Other Details",
   "link_type": "DocType",
   "onboard": 0,
   "type": "Card Break"
  },
  {
   "hidden": 0,
   "is_query_report": 0,
   "label": "Customers",
   "link_to": "Customer",
   "link_type": "DocType",
   "onboard": 0,
   "type": "Link"
  },
  {
   "dependencies": "",
   "hidden": 0,
   "is_query_report": 0,
   "label": "Property Owner",
   "link_to": "Customer",
   "link_type": "DocType",
   "onboard": 0,
   "type": "Link"
  },
  {
   "dependencies": "",
   "hidden": 0,
   "is_query_report": 0,
   "label": "Property Manager",
   "link_to": "Customer",
   "link_type": "DocType",
   "onboard": 0,
   "type": "Link"
  }
 ],
 "modified": "2022-10-05 12:14:23.443583",
 "modified_by": "Administrator",
 "module": "Property Management",
 "name": "Property Management",
 "owner": "Administrator",
 "pin_to_bottom": 0,
 "pin_to_top": 0,
 "shortcuts": [
  {
   "doc_view": "",
   "format": "",
   "label": "Customers",
   "link_to": "Customer",
   "stats_filter": "{\"is_customer\":[\"=\",\"1\"]}",
   "type": "DocType"
  },
  {
   "doc_view": "",
   "format": "",
   "label": "Property Owner",
   "link_to": "Customer",
   "stats_filter": "{\"is_property_owner\":[\"=\",\"1\"]}",
   "type": "DocType"
  },
  {
   "doc_view": "",
   "format": "",
   "label": "Property Manager",
   "link_to": "Customer",
   "stats_filter": "{\"is_property_manager\":[\"=\",\"1\"]}",
   "type": "DocType"
  },
  {
   "doc_view": "",
   "format": "",
   "label": "Tenant",
   "link_to": "Customer",
   "stats_filter": "{\"is_tenant\":[\"=\",\"1\"]}",
   "type": "DocType"
  },
  {
   "doc_view": "",
   "format": "",
   "label": "Landlord",
   "link_to": "Customer",
   "stats_filter": "{\"is_landlord\":[\"=\",\"1\"]}",
   "type": "DocType"
  },
  {
   "doc_view": "",
   "label": "Property Item",
   "link_to": "Item",
   "type": "DocType"
  },
  {
   "doc_view": "",
   "label": "Property",
   "link_to": "Asset",
   "type": "DocType"
  },
  {
   "doc_view": "",
   "label": "Tenancy",
   "link_to": "Tenancy",
   "type": "DocType"
  },
  {
   "doc_view": "Calendar",
   "label": "Tenancy Schedule",
   "link_to": "Event",
   "type": "DocType"
  }
 ]
}